flurry/__init__.py
flurry/app.c
flurry/app.cp36-win_amd64.pyd
flurry/exceptions.c
flurry/exceptions.cp36-win_amd64.pyd
flurry/handler.c
flurry/handler.cp36-win_amd64.pyd
flurry/request.c
flurry/request.cp36-win_amd64.pyd
flurry/response.c
flurry/response.cp36-win_amd64.pyd
flurry/server.c
flurry/server.cp36-win_amd64.pyd
flurry_ce-1.0.1.dist-info/LICENSE
flurry_ce-1.0.1.dist-info/METADATA
flurry_ce-1.0.1.dist-info/WHEEL
flurry_ce-1.0.1.dist-info/top_level.txt
flurry_ce-1.0.1.dist-info/RECORD
