Metadata-Version: 2.1
Name: flurry-ce
Version: 1.0.1
Summary: UNKNOWN
Home-page: https://github.com/onefeng/flurry
Author: onefeng
Author-email: 15198086902@163.com
License: MIT
Platform: UNKNOWN
Classifier: License :: OSI Approved :: MIT License
Classifier: Programming Language :: Python
Classifier: Programming Language :: Python :: 3
Classifier: Programming Language :: Python :: 3.6
Classifier: Programming Language :: Python :: Implementation :: CPython
Classifier: Programming Language :: Python :: Implementation :: PyPy
Requires-Python: >=3.7
License-File: LICENSE
Requires-Dist: Cython (==0.25.2)
Requires-Dist: httptools (==0.0.9)
Requires-Dist: uvloop (==0.8.0)
